pyexcel_htmlr/__init__.py
pyexcel_htmlr/_version.py
pyexcel_htmlr/htmlr.py
pyexcel_htmlr-0.6.0.dist-info/LICENSE
pyexcel_htmlr-0.6.0.dist-info/METADATA
pyexcel_htmlr-0.6.0.dist-info/WHEEL
pyexcel_htmlr-0.6.0.dist-info/top_level.txt
pyexcel_htmlr-0.6.0.dist-info/RECORD
