Metadata-Version: 2.1
Name: pyexcel-htmlr
Version: 0.6.0
Summary: read tables in html file as excel data
Home-page: https://github.com/pyexcel/pyexcel-htmlr
Author: chfw
Author-email: info@pyexcel.org
License: New BSD
Download-URL: https://github.com/pyexcel/pyexcel-htmlr/archive/0.6.0.tar.gz
Keywords: python
Platform: UNKNOWN
Classifier: Topic :: Software Development :: Libraries
Classifier: Programming Language :: Python
Classifier: Intended Audience :: Developers
Classifier: Programming Language :: Python :: 3 :: Only
Classifier: Programming Language :: Python :: 3.6
Classifier: Programming Language :: Python :: 3.7
Classifier: Programming Language :: Python :: 3.8
Classifier: License :: OSI Approved :: BSD License
Requires-Python: >=3.6
Requires-Dist: html5lib
Requires-Dist: lxml
Requires-Dist: pyexcel-io (>=0.6.2)
